pkdgrav2matlab/__init__.py
pkdgrav2matlab/__main__.py
pkdgrav2matlab-0.0.3.dist-info/LICENSE.txt
pkdgrav2matlab-0.0.3.dist-info/METADATA
pkdgrav2matlab-0.0.3.dist-info/WHEEL
pkdgrav2matlab-0.0.3.dist-info/entry_points.txt
pkdgrav2matlab-0.0.3.dist-info/top_level.txt
pkdgrav2matlab-0.0.3.dist-info/RECORD
