Metadata-Version: 2.1
Name: pkdgrav2matlab
Version: 0.0.3
Summary: A small package for converting pkdgrav binary output to matlab.
Home-page: https://github.com/cstatz/pkdgrav2matlab
Author: Christoph Statz
Author-email: christoph.statz@tu-dresden.de
License: UNKNOWN
Platform: UNKNOWN
Classifier: Programming Language :: Python :: 3
Classifier: Environment :: Console
Classifier: Intended Audience :: Developers
Classifier: Intended Audience :: Science/Research
Classifier: License :: OSI Approved :: BSD License
Classifier: Operating System :: OS Independent
Classifier: Topic :: Scientific/Engineering :: Physics
Classifier: Natural Language :: English
Requires-Python: >=3.6
Requires-Dist: argparse
Requires-Dist: numpy (>=1.18.0)
Requires-Dist: scipy (>=1.4.0)
